README.md
setup.py
lang/__init__.py
lang/files.py
lang/ids.py
lang/io.py
py_cli.egg-info/PKG-INFO
py_cli.egg-info/SOURCES.txt
py_cli.egg-info/dependency_links.txt
py_cli.egg-info/entry_points.txt
py_cli.egg-info/not-zip-safe
py_cli.egg-info/requires.txt
py_cli.egg-info/top_level.txt
xcli/__init__.py
xcli/apks.py
xcli/fir.py
xcli/invoke.py
xcli/oxs.py