Metadata-Version: 2.1
Name: py-cli
Version: 1.2.3
Summary: git-runner cli script
Home-page: https://pypi.org/project/py-cli/
Author: handy
Author-email: cvdnn@foxmail.com
License: Apache v2.0
Keywords: gitlab_runner_cli,android_cli
Platform: any
Provides-Extra: test
Provides-Extra: dev
